Metadata-Version: 2.1
Name: popframe
Version: 0.0.9
Summary: Provision assessment for cities of an urban region
Project-URL: Repository, https://github.com/Mvin8/PopFrame/
Project-URL: Bug Tracker, https://github.com/Mvin8/PopFrame/issues
Classifier: Programming Language :: Python :: 3
Classifier: License :: OSI Approved :: BSD License
Classifier: Operating System :: OS Independent
Classifier: Intended Audience :: Science/Research
Requires-Python: >=3.10
License-File: LICENSE
Requires-Dist: geopandas ==0.13.0
Requires-Dist: retrying ==1.3.4
Requires-Dist: contextily
Requires-Dist: mapclassify ==2.6.1
Requires-Dist: matplotlib ==3.7.1
Requires-Dist: matplotlib-inline ==0.1.6
Requires-Dist: networkx ==3.1
Requires-Dist: numpy ==1.23.5
Requires-Dist: osmnx ==1.6.0
Requires-Dist: pandas ==1.5.3
Requires-Dist: pyarrow ==12.0.0
Requires-Dist: pydantic ==2.7.2
Requires-Dist: pylint ==2.17.4
Requires-Dist: requests ==2.31.0
Requires-Dist: scikit-learn ==1.2.2
Requires-Dist: scipy ==1.10.1
Requires-Dist: shapely ==2.0.1
Requires-Dist: six ==1.16.0
Requires-Dist: tqdm ==4.65.0
Requires-Dist: seaborn ==0.12.2
Requires-Dist: folium ==0.14.0
Requires-Dist: dill ==0.3.8
Provides-Extra: dev
Requires-Dist: black[jupyter] >=22 ; extra == 'dev'
Requires-Dist: isort >=5.6 ; extra == 'dev'
Requires-Dist: pylint >=2.17 ; extra == 'dev'
Requires-Dist: pre-commit >=3.1 ; extra == 'dev'
Requires-Dist: sphinx ==6.2.1 ; extra == 'dev'
Requires-Dist: sphinx-book-theme ==1.0.1 ; extra == 'dev'
Requires-Dist: numpydoc ==1.5.0 ; extra == 'dev'
Requires-Dist: pytest ==7.4.3 ; extra == 'dev'
Requires-Dist: pytest-cov ==4.1.0 ; extra == 'dev'
